{
  "generatedAt": "2025-11-13T18:04:34.685Z",
  "results": {
    "steps": [
      {
        "id": "typecheck",
        "ok": true,
        "output": ""
      },
      {
        "id": "build",
        "ok": true,
        "output": ""
      },
      {
        "id": "coverage",
        "ok": false,
        "output": "\n\u001b[1m\u001b[7m\u001b[36m RUN \u001b[39m\u001b[27m\u001b[22m \u001b[36mv2.1.9 \u001b[39m\u001b[90mC:/Users/moji/nextgen-marketplace\u001b[39m\n      \u001b[2mCoverage enabled with \u001b[22m\u001b[33mv8\u001b[39m\n\n \u001b[32m✓\u001b[39m libs/payment/src/gateways/zarinpal.adapter.edge.test.ts \u001b[2m(\u001b[22m\u001b[2m5 tests\u001b[22m\u001b[2m)\u001b[22m\u001b[90m 8\u001b[2mms\u001b[22m\u001b[39m\n \u001b[32m✓\u001b[39m libs/payment/src/gateways/zarinpal.adapter.test.ts \u001b[2m(\u001b[22m\u001b[2m10 tests\u001b[22m\u001b[2m)\u001b[22m\u001b[90m 10\u001b[2mms\u001b[22m\u001b[39m\n \u001b[32m✓\u001b[39m libs/security/src/auditor.test.ts \u001b[2m(\u001b[22m\u001b[2m7 tests\u001b[22m\u001b[2m)\u001b[22m\u001b[90m 12\u001b[2mms\u001b[22m\u001b[39m\n \u001b[32m✓\u001b[39m libs/auth/src/core/audit-logger.test.ts \u001b[2m(\u001b[22m\u001b[2m4 tests\u001b[22m\u001b[2m)\u001b[22m\u001b[90m 6\u001b[2mms\u001b[22m\u001b[39m\n \u001b[32m✓\u001b[39m libs/security/src/token.test.ts \u001b[2m(\u001b[22m\u001b[2m8 tests\u001b[22m\u001b[2m)\u001b[22m\u001b[90m 7\u001b[2mms\u001b[22m\u001b[39m\n \u001b[32m✓\u001b[39m libs/auth/src/core/session-store.test.ts \u001b[2m(\u001b[22m\u001b[2m8 tests\u001b[22m\u001b[2m)\u001b[22m\u001b[90m 8\u001b[2mms\u001b[22m\u001b[39m\n \u001b[32m✓\u001b[39m libs/payment/src/services/reconciliation.service.test.ts \u001b[2m(\u001b[22m\u001b[2m1 test\u001b[22m\u001b[2m)\u001b[22m\u001b[90m 5\u001b[2mms\u001b[22m\u001b[39m\n \u001b[32m✓\u001b[39m libs/security/src/crypto.test.ts \u001b[2m(\u001b[22m\u001b[2m8 tests\u001b[22m\u001b[2m)\u001b[22m\u001b[90m 10\u001b[2mms\u001b[22m\u001b[39m\n \u001b[32m✓\u001b[39m libs/invoice/src/iran/iran-invoice.strategy.test.ts \u001b[2m(\u001b[22m\u001b[2m13 tests\u001b[22m\u001b[2m)\u001b[22m\u001b[90m 14\u001b[2mms\u001b[22m\u001b[39m\n \u001b[32m✓\u001b[39m libs/auth/src/core/token-manager.edge.test.ts \u001b[2m(\u001b[22m\u001b[2m5 tests\u001b[22m\u001b[2m)\u001b[22m\u001b[90m 7\u001b[2mms\u001b[22m\u001b[39m\n \u001b[32m✓\u001b[39m libs/auth/src/core/token-manager.test.ts \u001b[2m(\u001b[22m\u001b[2m8 tests\u001b[22m\u001b[2m)\u001b[22m\u001b[90m 8\u001b[2mms\u001b[22m\u001b[39m\n \u001b[32m✓\u001b[39m libs/security/src/fullCoverage.test.ts \u001b[2m(\u001b[22m\u001b[2m10 tests\u001b[22m\u001b[2m)\u001b[22m\u001b[90m 115\u001b[2mms\u001b[22m\u001b[39m\n \u001b[32m✓\u001b[39m libs/security/src/hashing.test.ts \u001b[2m(\u001b[22m\u001b[2m9 tests\u001b[22m\u001b[2m)\u001b[22m\u001b[33m 318\u001b[2mms\u001b[22m\u001b[39m\n \u001b[32m✓\u001b[39m tests/ai/chatbot.test.ts \u001b[2m(\u001b[22m\u001b[2m3 tests\u001b[22m\u001b[2m)\u001b[22m\u001b[33m 327\u001b[2mms\u001b[22m\u001b[39m\n \u001b[32m✓\u001b[39m libs/invoice/src/iran/iran-invoice.strategy.edge.test.ts \u001b[2m(\u001b[22m\u001b[2m3 tests\u001b[22m\u001b[2m)\u001b[22m\u001b[90m 8\u001b[2mms\u001b[22m\u001b[39m\n \u001b[32m✓\u001b[39m libs/ai/src/core/ai.service.test.ts \u001b[2m(\u001b[22m\u001b[2m3 tests\u001b[22m\u001b[2m)\u001b[22m\u001b[90m 45\u001b[2mms\u001b[22m\u001b[39m\n \u001b[32m✓\u001b[39m tests/theme/royal-theme.test.ts \u001b[2m(\u001b[22m\u001b[2m4 tests\u001b[22m\u001b[2m)\u001b[22m\u001b[90m 8\u001b[2mms\u001b[22m\u001b[39m\n \u001b[32m✓\u001b[39m libs/cooperation/src/iran/iran-bulk-pricing.strategy.test.ts \u001b[2m(\u001b[22m\u001b[2m4 tests\u001b[22m\u001b[2m)\u001b[22m\u001b[90m 5\u001b[2mms\u001b[22m\u001b[39m\n \u001b[32m✓\u001b[39m libs/auth/src/core/device-binding.test.ts \u001b[2m(\u001b[22m\u001b[2m6 tests\u001b[22m\u001b[2m)\u001b[22m\u001b[90m 6\u001b[2mms\u001b[22m\u001b[39m\n \u001b[32m✓\u001b[39m tests/ai/recommendation.test.ts \u001b[2m(\u001b[22m\u001b[2m2 tests\u001b[22m\u001b[2m)\u001b[22m\u001b[90m 9\u001b[2mms\u001b[22m\u001b[39m\n \u001b[32m✓\u001b[39m libs/auth/src/core/session-store.edge.test.ts \u001b[2m(\u001b[22m\u001b[2m2 tests\u001b[22m\u001b[2m)\u001b[22m\u001b[90m 5\u001b[2mms\u001b[22m\u001b[39m\n \u001b[32m✓\u001b[39m libs/fraud/src/iran/bank-markazi-rules.test.ts \u001b[2m(\u001b[22m\u001b[2m1 test\u001b[22m\u001b[2m)\u001b[22m\u001b[90m 5\u001b[2mms\u001b[22m\u001b[39m\n \u001b[32m✓\u001b[39m tests/ai/ui-adaptation.test.ts \u001b[2m(\u001b[22m\u001b[2m2 tests\u001b[22m\u001b[2m)\u001b[22m\u001b[90m 7\u001b[2mms\u001b[22m\u001b[39m\n \u001b[32m✓\u001b[39m tests/ai/semantic-search.test.ts \u001b[2m(\u001b[22m\u001b[2m4 tests\u001b[22m\u001b[2m)\u001b[22m\u001b[90m 6\u001b[2mms\u001b[22m\u001b[39m\n \u001b[32m✓\u001b[39m apps/web/src/app/(fa)/offline-client.test.tsx \u001b[2m(\u001b[22m\u001b[2m2 tests\u001b[22m\u001b[2m)\u001b[22m\u001b[90m 27\u001b[2mms\u001b[22m\u001b[39m\n \u001b[32m✓\u001b[39m tests/i18n.test.ts \u001b[2m(\u001b[22m\u001b[2m4 tests\u001b[22m\u001b[2m)\u001b[22m\u001b[90m 50\u001b[2mms\u001b[22m\u001b[39m\n \u001b[32m✓\u001b[39m libs/tax/src/iran/iran-tax-report.strategy.test.ts \u001b[2m(\u001b[22m\u001b[2m2 tests\u001b[22m\u001b[2m)\u001b[22m\u001b[90m 7\u001b[2mms\u001b[22m\u001b[39m\n \u001b[32m✓\u001b[39m apps/web/src/app/(fa)/(seller)/ai/page.test.tsx \u001b[2m(\u001b[22m\u001b[2m1 test\u001b[22m\u001b[2m)\u001b[22m\u001b[33m 311\u001b[2mms\u001b[22m\u001b[39m\n   \u001b[33m\u001b[2m✓\u001b[22m\u001b[39m (seller)/ai page (fa)\u001b[2m > \u001b[22mruns prediction and shows localized result \u001b[33m309\u001b[2mms\u001b[22m\u001b[39m\n \u001b[32m✓\u001b[39m libs/auth/src/core/audit-logger.edge.test.ts \u001b[2m(\u001b[22m\u001b[2m1 test\u001b[22m\u001b[2m)\u001b[22m\u001b[90m 4\u001b[2mms\u001b[22m\u001b[39m\n \u001b[32m✓\u001b[39m libs/auth/src/core/device-binding.branch.test.ts \u001b[2m(\u001b[22m\u001b[2m2 tests\u001b[22m\u001b[2m)\u001b[22m\u001b[90m 7\u001b[2mms\u001b[22m\u001b[39m\n \u001b[32m✓\u001b[39m libs/tax/src/iran/sena-integration.service.test.ts \u001b[2m(\u001b[22m\u001b[2m1 test\u001b[22m\u001b[2m)\u001b[22m\u001b[90m 5\u001b[2mms\u001b[22m\u001b[39m\n \u001b[32m✓\u001b[39m libs/payment/src/services/idempotency.service.test.ts \u001b[2m(\u001b[22m\u001b[2m2 tests\u001b[22m\u001b[2m)\u001b[22m\u001b[90m 5\u001b[2mms\u001b[22m\u001b[39m\n \u001b[32m✓\u001b[39m libs/security/src/secrets.test.ts \u001b[2m(\u001b[22m\u001b[2m3 tests\u001b[22m\u001b[2m)\u001b[22m\u001b[90m 6\u001b[2mms\u001b[22m\u001b[39m\n \u001b[32m✓\u001b[39m libs/auth/src/core/device-binding.edge.test.ts \u001b[2m(\u001b[22m\u001b[2m2 tests\u001b[22m\u001b[2m)\u001b[22m\u001b[90m 5\u001b[2mms\u001b[22m\u001b[39m\n \u001b[32m✓\u001b[39m libs/auth/src/rotation.test.ts \u001b[2m(\u001b[22m\u001b[2m2 tests\u001b[22m\u001b[2m)\u001b[22m\u001b[90m 6\u001b[2mms\u001b[22m\u001b[39m\n \u001b[32m✓\u001b[39m libs/auth/src/replay.test.ts \u001b[2m(\u001b[22m\u001b[2m2 tests\u001b[22m\u001b[2m)\u001b[22m\u001b[90m 5\u001b[2mms\u001b[22m\u001b[39m\n \u001b[32m✓\u001b[39m libs/payment/src/services/idempotency.service.edge.test.ts \u001b[2m(\u001b[22m\u001b[2m2 tests\u001b[22m\u001b[2m)\u001b[22m\u001b[90m 5\u001b[2mms\u001b[22m\u001b[39m\n \u001b[32m✓\u001b[39m libs/cooperation/src/group-settlement.service.test.ts \u001b[2m(\u001b[22m\u001b[2m2 tests\u001b[22m\u001b[2m)\u001b[22m\u001b[90m 6\u001b[2mms\u001b[22m\u001b[39m\n \u001b[32m✓\u001b[39m libs/invoice/src/iran/jalali-date.edge.test.ts \u001b[2m(\u001b[22m\u001b[2m2 tests\u001b[22m\u001b[2m)\u001b[22m\u001b[90m 6\u001b[2mms\u001b[22m\u001b[39m\n \u001b[32m✓\u001b[39m apps/web/src/app/(fa)/layout.test.tsx \u001b[2m(\u001b[22m\u001b[2m1 test\u001b[22m\u001b[2m)\u001b[22m\u001b[90m 126\u001b[2mms\u001b[22m\u001b[39m\n \u001b[32m✓\u001b[39m libs/security/src/rbac.test.ts \u001b[2m(\u001b[22m\u001b[2m4 tests\u001b[22m\u001b[2m)\u001b[22m\u001b[90m 7\u001b[2mms\u001b[22m\u001b[39m\n \u001b[32m✓\u001b[39m apps/web/src/components/ui/persian-date-picker.test.tsx \u001b[2m(\u001b[22m\u001b[2m1 test\u001b[22m\u001b[2m)\u001b[22m\u001b[90m 78\u001b[2mms\u001b[22m\u001b[39m\n \u001b[32m✓\u001b[39m libs/security/src/timing.test.ts \u001b[2m(\u001b[22m\u001b[2m4 tests\u001b[22m\u001b[2m)\u001b[22m\u001b[33m 4840\u001b[2mms\u001b[22m\u001b[39m\n   \u001b[33m\u001b[2m✓\u001b[22m\u001b[39m timing\u001b[2m > \u001b[22mverifyPassword timing variance bounded \u001b[33m4831\u001b[2mms\u001b[22m\u001b[39m\n \u001b[32m✓\u001b[39m libs/payment/src/index.test.ts \u001b[2m(\u001b[22m\u001b[2m2 tests\u001b[22m\u001b[2m)\u001b[22m\u001b[90m 5\u001b[2mms\u001b[22m\u001b[39m\n \u001b[32m✓\u001b[39m libs/payment/src/types.test.ts \u001b[2m(\u001b[22m\u001b[2m2 tests\u001b[22m\u001b[2m)\u001b[22m\u001b[90m 6\u001b[2mms\u001b[22m\u001b[39m\n \u001b[32m✓\u001b[39m libs/invoice/src/iran/render-pdf.test.ts \u001b[2m(\u001b[22m\u001b[2m1 test\u001b[22m\u001b[2m)\u001b[22m\u001b[90m 5\u001b[2mms\u001b[22m\u001b[39m\n \u001b[32m✓\u001b[39m libs/cooperation/src/reputation.service.test.ts \u001b[2m(\u001b[22m\u001b[2m1 test\u001b[22m\u001b[2m)\u001b[22m\u001b[90m 4\u001b[2mms\u001b[22m\u001b[39m\n \u001b[32m✓\u001b[39m libs/auth/src/core/index.test.ts \u001b[2m(\u001b[22m\u001b[2m1 test\u001b[22m\u001b[2m)\u001b[22m\u001b[90m 5\u001b[2mms\u001b[22m\u001b[39m\n \u001b[32m✓\u001b[39m apps/web/src/components/ui/persian-date-utils.test.tsx \u001b[2m(\u001b[22m\u001b[2m1 test\u001b[22m\u001b[2m)\u001b[22m\u001b[90m 5\u001b[2mms\u001b[22m\u001b[39m\n \u001b[32m✓\u001b[39m libs/security/src/index.test.ts \u001b[2m(\u001b[22m\u001b[2m1 test\u001b[22m\u001b[2m)\u001b[22m\u001b[90m 6\u001b[2mms\u001b[22m\u001b[39m\n \u001b[32m✓\u001b[39m libs/auth/src/audit.test.ts \u001b[2m(\u001b[22m\u001b[2m1 test\u001b[22m\u001b[2m)\u001b[22m\u001b[90m 5\u001b[2mms\u001b[22m\u001b[39m\n \u001b[32m✓\u001b[39m apps/web/src/app/(fa)/(admin)/tax-reports/page.test.tsx \u001b[2m(\u001b[22m\u001b[2m1 test\u001b[22m\u001b[2m)\u001b[22m\u001b[90m 43\u001b[2mms\u001b[22m\u001b[39m\n \u001b[32m✓\u001b[39m libs/auth/src/index.test.ts \u001b[2m(\u001b[22m\u001b[2m1 test\u001b[22m\u001b[2m)\u001b[22m\u001b[90m 3\u001b[2mms\u001b[22m\u001b[39m\n \u001b[32m✓\u001b[39m apps/web/src/app/(fa)/page.test.tsx \u001b[2m(\u001b[22m\u001b[2m1 test\u001b[22m\u001b[2m)\u001b[22m\u001b[90m 54\u001b[2mms\u001b[22m\u001b[39m\n \u001b[32m✓\u001b[39m apps/web/src/app/(fa)/(admin)/sena/page.test.tsx \u001b[2m(\u001b[22m\u001b[2m1 test\u001b[22m\u001b[2m)\u001b[22m\u001b[90m 42\u001b[2mms\u001b[22m\u001b[39m\n \u001b[32m✓\u001b[39m libs/invoice/src/index.test.ts \u001b[2m(\u001b[22m\u001b[2m1 test\u001b[22m\u001b[2m)\u001b[22m\u001b[90m 4\u001b[2mms\u001b[22m\u001b[39m\n \u001b[32m✓\u001b[39m apps/web/src/app/(fa)/seller/dashboard/page.test.tsx \u001b[2m(\u001b[22m\u001b[2m1 test\u001b[22m\u001b[2m)\u001b[22m\u001b[90m 69\u001b[2mms\u001b[22m\u001b[39m\n \u001b[32m✓\u001b[39m apps/web/src/app/(fa)/(cooperation)/marketplace/page.test.tsx \u001b[2m(\u001b[22m\u001b[2m1 test\u001b[22m\u001b[2m)\u001b[22m\u001b[90m 41\u001b[2mms\u001b[22m\u001b[39m\n \u001b[32m✓\u001b[39m libs/auth/src/mtls.test.ts \u001b[2m(\u001b[22m\u001b[2m1 test\u001b[22m\u001b[2m)\u001b[22m\u001b[90m 4\u001b[2mms\u001b[22m\u001b[39m\n \u001b[32m✓\u001b[39m libs/security/src/rbac.model.test.ts \u001b[2m(\u001b[22m\u001b[2m1 test\u001b[22m\u001b[2m)\u001b[22m\u001b[90m 3\u001b[2mms\u001b[22m\u001b[39m\n\n\u001b[2m Test Files \u001b[22m \u001b[1m\u001b[32m60 passed\u001b[39m\u001b[22m\u001b[90m (60)\u001b[39m\n\u001b[2m      Tests \u001b[22m \u001b[1m\u001b[32m189 passed\u001b[39m\u001b[22m\u001b[90m (189)\u001b[39m\n\u001b[2m   Start at \u001b[22m 21:34:09\n\u001b[2m   Duration \u001b[22m 8.79s\u001b[2m (transform 1.77s, setup 0ms, collect 7.52s, tests 6.77s, environment 71.07s, prepare 10.16s)\u001b[22m\n\n\u001b[34m % \u001b[39m\u001b[2mCoverage report from \u001b[22m\u001b[33mv8\u001b[39m\n-------------------|---------|----------|---------|---------|-------------------\nFile               | % Stmts | % Branch | % Funcs | % Lines | Uncovered Line #s \n-------------------|---------|----------|---------|---------|-------------------\nAll files          |   98.92 |    96.76 |   96.74 |   98.92 |                   \n ...b/src/app/(fa) |   87.27 |       70 |      60 |   87.27 |                   \n  layout.tsx       |   89.65 |       50 |      50 |   89.65 | 17-19             \n  ...ne-client.tsx |   78.94 |       80 |      50 |   78.94 | 16-18,22          \n  page.tsx         |     100 |      100 |     100 |     100 |                   \n ...)/(admin)/sena |     100 |      100 |     100 |     100 |                   \n  page.tsx         |     100 |      100 |     100 |     100 |                   \n ...n)/tax-reports |     100 |      100 |     100 |     100 |                   \n  page.tsx         |     100 |      100 |     100 |     100 |                   \n ...n)/marketplace |     100 |      100 |     100 |     100 |                   \n  page.tsx         |     100 |      100 |     100 |     100 |                   \n ...a)/(seller)/ai |     100 |      100 |   66.66 |     100 |                   \n  page.tsx         |     100 |      100 |   66.66 |     100 |                   \n ...ller/dashboard |     100 |      100 |     100 |     100 |                   \n  page.tsx         |     100 |      100 |     100 |     100 |                   \n .../components/ui |     100 |    57.14 |     100 |     100 |                   \n  ...te-picker.tsx |     100 |    57.14 |     100 |     100 | 6,11,19           \n libs/auth/src     |     100 |      100 |     100 |     100 |                   \n  audit.ts         |     100 |      100 |     100 |     100 |                   \n  index.ts         |     100 |      100 |     100 |     100 |                   \n  mtls.ts          |     100 |      100 |     100 |     100 |                   \n  replay.ts        |     100 |      100 |     100 |     100 |                   \n  rotation.ts      |     100 |      100 |     100 |     100 |                   \n .../auth/src/core |     100 |    98.61 |     100 |     100 |                   \n  audit-logger.ts  |     100 |      100 |     100 |     100 |                   \n  ...ce-binding.ts |     100 |      100 |     100 |     100 |                   \n  index.ts         |     100 |      100 |     100 |     100 |                   \n  session-store.ts |     100 |      100 |     100 |     100 |                   \n  token-manager.ts |     100 |       95 |     100 |     100 | 20                \n libs/invoice/src  |     100 |      100 |     100 |     100 |                   \n  index.ts         |     100 |      100 |     100 |     100 |                   \n  types.ts         |       0 |        0 |       0 |       0 |                   \n ...voice/src/iran |     100 |    96.07 |   95.23 |     100 |                   \n  ...e.strategy.ts |     100 |    94.11 |   93.75 |     100 | 12,44             \n  ...calculator.ts |     100 |      100 |     100 |     100 |                   \n  ...te.service.ts |     100 |      100 |     100 |     100 |                   \n libs/payment/src  |     100 |      100 |     100 |     100 |                   \n  index.ts         |     100 |      100 |     100 |     100 |                   \n  types.ts         |     100 |      100 |     100 |     100 |                   \n ...t/src/gateways |     100 |    96.77 |     100 |     100 |                   \n  ...al.adapter.ts |     100 |    96.77 |     100 |     100 | 14                \n ...t/src/services |     100 |      100 |     100 |     100 |                   \n  ...cy.service.ts |     100 |      100 |     100 |     100 |                   \n  ...on.service.ts |     100 |      100 |     100 |     100 |                   \n libs/security/src |     100 |      100 |     100 |     100 |                   \n  auditor.ts       |     100 |      100 |     100 |     100 |                   \n  crypto.ts        |     100 |      100 |     100 |     100 |                   \n  hashing.ts       |     100 |      100 |     100 |     100 |                   \n  index.ts         |     100 |      100 |     100 |     100 |                   \n  rbac.ts          |     100 |      100 |     100 |     100 |                   \n  secrets.ts       |     100 |      100 |     100 |     100 |                   \n  token.ts         |     100 |      100 |     100 |     100 |                   \n ...urity/src/rbac |     100 |      100 |     100 |     100 |                   \n  model.ts         |     100 |      100 |     100 |     100 |                   \n-------------------|---------|----------|---------|---------|-------------------\n"
      },
      {
        "id": "api-validation",
        "ok": false,
        "output": ""
      },
      {
        "id": "security-auditor-final",
        "ok": true,
        "output": "[security-auditor-final] Report saved to C:\\Users\\moji\\nextgen-marketplace\\ops\\reports\\security-audit-final.json"
      },
      {
        "id": "self-critique",
        "ok": false,
        "output": "\n\u001b[1m\u001b[7m\u001b[36m RUN \u001b[39m\u001b[27m\u001b[22m \u001b[36mv2.1.9 \u001b[39m\u001b[90mC:/Users/moji/nextgen-marketplace\u001b[39m\n      \u001b[2mCoverage enabled with \u001b[22m\u001b[33mv8\u001b[39m\n\n \u001b[32m✓\u001b[39m libs/payment/src/gateways/zarinpal.adapter.edge.test.ts \u001b[2m(\u001b[22m\u001b[2m5 tests\u001b[22m\u001b[2m)\u001b[22m\u001b[90m 9\u001b[2mms\u001b[22m\u001b[39m\n \u001b[32m✓\u001b[39m libs/auth/src/core/session-store.test.ts \u001b[2m(\u001b[22m\u001b[2m8 tests\u001b[22m\u001b[2m)\u001b[22m\u001b[90m 8\u001b[2mms\u001b[22m\u001b[39m\n \u001b[32m✓\u001b[39m libs/payment/src/gateways/zarinpal.adapter.test.ts \u001b[2m(\u001b[22m\u001b[2m10 tests\u001b[22m\u001b[2m)\u001b[22m\u001b[90m 12\u001b[2mms\u001b[22m\u001b[39m\n \u001b[32m✓\u001b[39m libs/security/src/token.test.ts \u001b[2m(\u001b[22m\u001b[2m8 tests\u001b[22m\u001b[2m)\u001b[22m\u001b[90m 7\u001b[2mms\u001b[22m\u001b[39m\n \u001b[32m✓\u001b[39m libs/security/src/crypto.test.ts \u001b[2m(\u001b[22m\u001b[2m8 tests\u001b[22m\u001b[2m)\u001b[22m\u001b[90m 10\u001b[2mms\u001b[22m\u001b[39m\n \u001b[32m✓\u001b[39m libs/auth/src/core/audit-logger.test.ts \u001b[2m(\u001b[22m\u001b[2m4 tests\u001b[22m\u001b[2m)\u001b[22m\u001b[90m 5\u001b[2mms\u001b[22m\u001b[39m\n \u001b[32m✓\u001b[39m libs/security/src/auditor.test.ts \u001b[2m(\u001b[22m\u001b[2m7 tests\u001b[22m\u001b[2m)\u001b[22m\u001b[90m 11\u001b[2mms\u001b[22m\u001b[39m\n \u001b[32m✓\u001b[39m libs/payment/src/services/reconciliation.service.test.ts \u001b[2m(\u001b[22m\u001b[2m1 test\u001b[22m\u001b[2m)\u001b[22m\u001b[90m 5\u001b[2mms\u001b[22m\u001b[39m\n \u001b[32m✓\u001b[39m libs/invoice/src/iran/iran-invoice.strategy.test.ts \u001b[2m(\u001b[22m\u001b[2m13 tests\u001b[22m\u001b[2m)\u001b[22m\u001b[90m 16\u001b[2mms\u001b[22m\u001b[39m\n \u001b[32m✓\u001b[39m libs/security/src/fullCoverage.test.ts \u001b[2m(\u001b[22m\u001b[2m10 tests\u001b[22m\u001b[2m)\u001b[22m\u001b[90m 114\u001b[2mms\u001b[22m\u001b[39m\n \u001b[32m✓\u001b[39m libs/auth/src/core/token-manager.edge.test.ts \u001b[2m(\u001b[22m\u001b[2m5 tests\u001b[22m\u001b[2m)\u001b[22m\u001b[90m 7\u001b[2mms\u001b[22m\u001b[39m\n \u001b[32m✓\u001b[39m libs/auth/src/core/token-manager.test.ts \u001b[2m(\u001b[22m\u001b[2m8 tests\u001b[22m\u001b[2m)\u001b[22m\u001b[90m 9\u001b[2mms\u001b[22m\u001b[39m\n \u001b[32m✓\u001b[39m libs/security/src/hashing.test.ts \u001b[2m(\u001b[22m\u001b[2m9 tests\u001b[22m\u001b[2m)\u001b[22m\u001b[33m 308\u001b[2mms\u001b[22m\u001b[39m\n \u001b[32m✓\u001b[39m tests/ai/chatbot.test.ts \u001b[2m(\u001b[22m\u001b[2m3 tests\u001b[22m\u001b[2m)\u001b[22m\u001b[33m 319\u001b[2mms\u001b[22m\u001b[39m\n \u001b[32m✓\u001b[39m libs/auth/src/core/device-binding.test.ts \u001b[2m(\u001b[22m\u001b[2m6 tests\u001b[22m\u001b[2m)\u001b[22m\u001b[90m 6\u001b[2mms\u001b[22m\u001b[39m\n \u001b[32m✓\u001b[39m libs/ai/src/core/ai.service.test.ts \u001b[2m(\u001b[22m\u001b[2m3 tests\u001b[22m\u001b[2m)\u001b[22m\u001b[90m 30\u001b[2mms\u001b[22m\u001b[39m\n \u001b[32m✓\u001b[39m tests/ai/recommendation.test.ts \u001b[2m(\u001b[22m\u001b[2m2 tests\u001b[22m\u001b[2m)\u001b[22m\u001b[90m 8\u001b[2mms\u001b[22m\u001b[39m\n \u001b[32m✓\u001b[39m tests/theme/royal-theme.test.ts \u001b[2m(\u001b[22m\u001b[2m4 tests\u001b[22m\u001b[2m)\u001b[22m\u001b[90m 7\u001b[2mms\u001b[22m\u001b[39m\n \u001b[32m✓\u001b[39m libs/invoice/src/iran/iran-invoice.strategy.edge.test.ts \u001b[2m(\u001b[22m\u001b[2m3 tests\u001b[22m\u001b[2m)\u001b[22m\u001b[90m 8\u001b[2mms\u001b[22m\u001b[39m\n \u001b[32m✓\u001b[39m tests/ai/ui-adaptation.test.ts \u001b[2m(\u001b[22m\u001b[2m2 tests\u001b[22m\u001b[2m)\u001b[22m\u001b[90m 7\u001b[2mms\u001b[22m\u001b[39m\n \u001b[32m✓\u001b[39m libs/fraud/src/iran/bank-markazi-rules.test.ts \u001b[2m(\u001b[22m\u001b[2m1 test\u001b[22m\u001b[2m)\u001b[22m\u001b[90m 7\u001b[2mms\u001b[22m\u001b[39m\n \u001b[32m✓\u001b[39m libs/auth/src/core/session-store.edge.test.ts \u001b[2m(\u001b[22m\u001b[2m2 tests\u001b[22m\u001b[2m)\u001b[22m\u001b[90m 5\u001b[2mms\u001b[22m\u001b[39m\n \u001b[32m✓\u001b[39m libs/cooperation/src/iran/iran-bulk-pricing.strategy.test.ts \u001b[2m(\u001b[22m\u001b[2m4 tests\u001b[22m\u001b[2m)\u001b[22m\u001b[90m 5\u001b[2mms\u001b[22m\u001b[39m\n \u001b[32m✓\u001b[39m tests/ai/semantic-search.test.ts \u001b[2m(\u001b[22m\u001b[2m4 tests\u001b[22m\u001b[2m)\u001b[22m\u001b[90m 7\u001b[2mms\u001b[22m\u001b[39m\n \u001b[32m✓\u001b[39m apps/web/src/app/(fa)/offline-client.test.tsx \u001b[2m(\u001b[22m\u001b[2m2 tests\u001b[22m\u001b[2m)\u001b[22m\u001b[90m 31\u001b[2mms\u001b[22m\u001b[39m\n \u001b[32m✓\u001b[39m tests/i18n.test.ts \u001b[2m(\u001b[22m\u001b[2m4 tests\u001b[22m\u001b[2m)\u001b[22m\u001b[90m 47\u001b[2mms\u001b[22m\u001b[39m\n \u001b[32m✓\u001b[39m libs/tax/src/iran/iran-tax-report.strategy.test.ts \u001b[2m(\u001b[22m\u001b[2m2 tests\u001b[22m\u001b[2m)\u001b[22m\u001b[90m 5\u001b[2mms\u001b[22m\u001b[39m\n \u001b[32m✓\u001b[39m apps/web/src/app/(fa)/(seller)/ai/page.test.tsx \u001b[2m(\u001b[22m\u001b[2m1 test\u001b[22m\u001b[2m)\u001b[22m\u001b[90m 297\u001b[2mms\u001b[22m\u001b[39m\n \u001b[32m✓\u001b[39m libs/auth/src/core/audit-logger.edge.test.ts \u001b[2m(\u001b[22m\u001b[2m1 test\u001b[22m\u001b[2m)\u001b[22m\u001b[90m 4\u001b[2mms\u001b[22m\u001b[39m\n \u001b[32m✓\u001b[39m libs/payment/src/services/idempotency.service.test.ts \u001b[2m(\u001b[22m\u001b[2m2 tests\u001b[22m\u001b[2m)\u001b[22m\u001b[90m 5\u001b[2mms\u001b[22m\u001b[39m\n \u001b[32m✓\u001b[39m libs/tax/src/iran/sena-integration.service.test.ts \u001b[2m(\u001b[22m\u001b[2m1 test\u001b[22m\u001b[2m)\u001b[22m\u001b[90m 5\u001b[2mms\u001b[22m\u001b[39m\n \u001b[32m✓\u001b[39m libs/auth/src/core/device-binding.branch.test.ts \u001b[2m(\u001b[22m\u001b[2m2 tests\u001b[22m\u001b[2m)\u001b[22m\u001b[90m 6\u001b[2mms\u001b[22m\u001b[39m\n \u001b[32m✓\u001b[39m libs/auth/src/replay.test.ts \u001b[2m(\u001b[22m\u001b[2m2 tests\u001b[22m\u001b[2m)\u001b[22m\u001b[90m 6\u001b[2mms\u001b[22m\u001b[39m\n \u001b[32m✓\u001b[39m libs/security/src/secrets.test.ts \u001b[2m(\u001b[22m\u001b[2m3 tests\u001b[22m\u001b[2m)\u001b[22m\u001b[90m 7\u001b[2mms\u001b[22m\u001b[39m\n \u001b[32m✓\u001b[39m libs/auth/src/core/device-binding.edge.test.ts \u001b[2m(\u001b[22m\u001b[2m2 tests\u001b[22m\u001b[2m)\u001b[22m\u001b[90m 5\u001b[2mms\u001b[22m\u001b[39m\n \u001b[32m✓\u001b[39m libs/auth/src/rotation.test.ts \u001b[2m(\u001b[22m\u001b[2m2 tests\u001b[22m\u001b[2m)\u001b[22m\u001b[90m 6\u001b[2mms\u001b[22m\u001b[39m\n \u001b[32m✓\u001b[39m libs/payment/src/services/idempotency.service.edge.test.ts \u001b[2m(\u001b[22m\u001b[2m2 tests\u001b[22m\u001b[2m)\u001b[22m\u001b[90m 4\u001b[2mms\u001b[22m\u001b[39m\n \u001b[32m✓\u001b[39m libs/cooperation/src/group-settlement.service.test.ts \u001b[2m(\u001b[22m\u001b[2m2 tests\u001b[22m\u001b[2m)\u001b[22m\u001b[90m 7\u001b[2mms\u001b[22m\u001b[39m\n \u001b[32m✓\u001b[39m libs/invoice/src/iran/jalali-date.edge.test.ts \u001b[2m(\u001b[22m\u001b[2m2 tests\u001b[22m\u001b[2m)\u001b[22m\u001b[90m 6\u001b[2mms\u001b[22m\u001b[39m\n \u001b[32m✓\u001b[39m apps/web/src/app/(fa)/layout.test.tsx \u001b[2m(\u001b[22m\u001b[2m1 test\u001b[22m\u001b[2m)\u001b[22m\u001b[90m 130\u001b[2mms\u001b[22m\u001b[39m\n \u001b[32m✓\u001b[39m libs/security/src/rbac.test.ts \u001b[2m(\u001b[22m\u001b[2m4 tests\u001b[22m\u001b[2m)\u001b[22m\u001b[90m 6\u001b[2mms\u001b[22m\u001b[39m\n \u001b[32m✓\u001b[39m apps/web/src/components/ui/persian-date-picker.test.tsx \u001b[2m(\u001b[22m\u001b[2m1 test\u001b[22m\u001b[2m)\u001b[22m\u001b[90m 78\u001b[2mms\u001b[22m\u001b[39m\n \u001b[32m✓\u001b[39m libs/security/src/timing.test.ts \u001b[2m(\u001b[22m\u001b[2m4 tests\u001b[22m\u001b[2m)\u001b[22m\u001b[33m 4865\u001b[2mms\u001b[22m\u001b[39m\n   \u001b[33m\u001b[2m✓\u001b[22m\u001b[39m timing\u001b[2m > \u001b[22mverifyPassword timing variance bounded \u001b[33m4856\u001b[2mms\u001b[22m\u001b[39m\n \u001b[32m✓\u001b[39m libs/payment/src/types.test.ts \u001b[2m(\u001b[22m\u001b[2m2 tests\u001b[22m\u001b[2m)\u001b[22m\u001b[90m 7\u001b[2mms\u001b[22m\u001b[39m\n \u001b[32m✓\u001b[39m libs/invoice/src/iran/render-pdf.test.ts \u001b[2m(\u001b[22m\u001b[2m1 test\u001b[22m\u001b[2m)\u001b[22m\u001b[90m 5\u001b[2mms\u001b[22m\u001b[39m\n \u001b[32m✓\u001b[39m libs/payment/src/index.test.ts \u001b[2m(\u001b[22m\u001b[2m2 tests\u001b[22m\u001b[2m)\u001b[22m\u001b[90m 5\u001b[2mms\u001b[22m\u001b[39m\n \u001b[32m✓\u001b[39m libs/cooperation/src/reputation.service.test.ts \u001b[2m(\u001b[22m\u001b[2m1 test\u001b[22m\u001b[2m)\u001b[22m\u001b[90m 4\u001b[2mms\u001b[22m\u001b[39m\n \u001b[32m✓\u001b[39m libs/auth/src/core/index.test.ts \u001b[2m(\u001b[22m\u001b[2m1 test\u001b[22m\u001b[2m)\u001b[22m\u001b[90m 4\u001b[2mms\u001b[22m\u001b[39m\n \u001b[32m✓\u001b[39m apps/web/src/components/ui/persian-date-utils.test.tsx \u001b[2m(\u001b[22m\u001b[2m1 test\u001b[22m\u001b[2m)\u001b[22m\u001b[90m 4\u001b[2mms\u001b[22m\u001b[39m\n \u001b[32m✓\u001b[39m libs/security/src/index.test.ts \u001b[2m(\u001b[22m\u001b[2m1 test\u001b[22m\u001b[2m)\u001b[22m\u001b[90m 5\u001b[2mms\u001b[22m\u001b[39m\n \u001b[32m✓\u001b[39m libs/auth/src/audit.test.ts \u001b[2m(\u001b[22m\u001b[2m1 test\u001b[22m\u001b[2m)\u001b[22m\u001b[90m 4\u001b[2mms\u001b[22m\u001b[39m\n \u001b[32m✓\u001b[39m apps/web/src/app/(fa)/(admin)/tax-reports/page.test.tsx \u001b[2m(\u001b[22m\u001b[2m1 test\u001b[22m\u001b[2m)\u001b[22m\u001b[90m 46\u001b[2mms\u001b[22m\u001b[39m\n \u001b[32m✓\u001b[39m apps/web/src/app/(fa)/page.test.tsx \u001b[2m(\u001b[22m\u001b[2m1 test\u001b[22m\u001b[2m)\u001b[22m\u001b[90m 49\u001b[2mms\u001b[22m\u001b[39m\n \u001b[32m✓\u001b[39m apps/web/src/app/(fa)/(admin)/sena/page.test.tsx \u001b[2m(\u001b[22m\u001b[2m1 test\u001b[22m\u001b[2m)\u001b[22m\u001b[90m 51\u001b[2mms\u001b[22m\u001b[39m\n \u001b[32m✓\u001b[39m libs/auth/src/index.test.ts \u001b[2m(\u001b[22m\u001b[2m1 test\u001b[22m\u001b[2m)\u001b[22m\u001b[90m 4\u001b[2mms\u001b[22m\u001b[39m\n \u001b[32m✓\u001b[39m libs/invoice/src/index.test.ts \u001b[2m(\u001b[22m\u001b[2m1 test\u001b[22m\u001b[2m)\u001b[22m\u001b[90m 3\u001b[2mms\u001b[22m\u001b[39m\n \u001b[32m✓\u001b[39m apps/web/src/app/(fa)/seller/dashboard/page.test.tsx \u001b[2m(\u001b[22m\u001b[2m1 test\u001b[22m\u001b[2m)\u001b[22m\u001b[90m 73\u001b[2mms\u001b[22m\u001b[39m\n \u001b[32m✓\u001b[39m libs/auth/src/mtls.test.ts \u001b[2m(\u001b[22m\u001b[2m1 test\u001b[22m\u001b[2m)\u001b[22m\u001b[90m 4\u001b[2mms\u001b[22m\u001b[39m\n \u001b[32m✓\u001b[39m libs/security/src/rbac.model.test.ts \u001b[2m(\u001b[22m\u001b[2m1 test\u001b[22m\u001b[2m)\u001b[22m\u001b[90m 3\u001b[2mms\u001b[22m\u001b[39m\n \u001b[32m✓\u001b[39m apps/web/src/app/(fa)/(cooperation)/marketplace/page.test.tsx \u001b[2m(\u001b[22m\u001b[2m1 test\u001b[22m\u001b[2m)\u001b[22m\u001b[90m 28\u001b[2mms\u001b[22m\u001b[39m\n\n\u001b[2m Test Files \u001b[22m \u001b[1m\u001b[32m60 passed\u001b[39m\u001b[22m\u001b[90m (60)\u001b[39m\n\u001b[2m      Tests \u001b[22m \u001b[1m\u001b[32m189 passed\u001b[39m\u001b[22m\u001b[90m (189)\u001b[39m\n\u001b[2m   Start at \u001b[22m 21:34:22\n\u001b[2m   Duration \u001b[22m 8.82s\u001b[2m (transform 1.63s, setup 0ms, collect 7.43s, tests 6.75s, environment 74.14s, prepare 10.44s)\u001b[22m\n\n\u001b[34m % \u001b[39m\u001b[2mCoverage report from \u001b[22m\u001b[33mv8\u001b[39m\n-------------------|---------|----------|---------|---------|-------------------\nFile               | % Stmts | % Branch | % Funcs | % Lines | Uncovered Line #s \n-------------------|---------|----------|---------|---------|-------------------\nAll files          |   98.92 |    96.76 |   96.74 |   98.92 |                   \n ...b/src/app/(fa) |   87.27 |       70 |      60 |   87.27 |                   \n  layout.tsx       |   89.65 |       50 |      50 |   89.65 | 17-19             \n  ...ne-client.tsx |   78.94 |       80 |      50 |   78.94 | 16-18,22          \n  page.tsx         |     100 |      100 |     100 |     100 |                   \n ...)/(admin)/sena |     100 |      100 |     100 |     100 |                   \n  page.tsx         |     100 |      100 |     100 |     100 |                   \n ...n)/tax-reports |     100 |      100 |     100 |     100 |                   \n  page.tsx         |     100 |      100 |     100 |     100 |                   \n ...n)/marketplace |     100 |      100 |     100 |     100 |                   \n  page.tsx         |     100 |      100 |     100 |     100 |                   \n ...a)/(seller)/ai |     100 |      100 |   66.66 |     100 |                   \n  page.tsx         |     100 |      100 |   66.66 |     100 |                   \n ...ller/dashboard |     100 |      100 |     100 |     100 |                   \n  page.tsx         |     100 |      100 |     100 |     100 |                   \n .../components/ui |     100 |    57.14 |     100 |     100 |                   \n  ...te-picker.tsx |     100 |    57.14 |     100 |     100 | 6,11,19           \n libs/auth/src     |     100 |      100 |     100 |     100 |                   \n  audit.ts         |     100 |      100 |     100 |     100 |                   \n  index.ts         |     100 |      100 |     100 |     100 |                   \n  mtls.ts          |     100 |      100 |     100 |     100 |                   \n  replay.ts        |     100 |      100 |     100 |     100 |                   \n  rotation.ts      |     100 |      100 |     100 |     100 |                   \n .../auth/src/core |     100 |    98.61 |     100 |     100 |                   \n  audit-logger.ts  |     100 |      100 |     100 |     100 |                   \n  ...ce-binding.ts |     100 |      100 |     100 |     100 |                   \n  index.ts         |     100 |      100 |     100 |     100 |                   \n  session-store.ts |     100 |      100 |     100 |     100 |                   \n  token-manager.ts |     100 |       95 |     100 |     100 | 20                \n libs/invoice/src  |     100 |      100 |     100 |     100 |                   \n  index.ts         |     100 |      100 |     100 |     100 |                   \n  types.ts         |       0 |        0 |       0 |       0 |                   \n ...voice/src/iran |     100 |    96.07 |   95.23 |     100 |                   \n  ...e.strategy.ts |     100 |    94.11 |   93.75 |     100 | 12,44             \n  ...calculator.ts |     100 |      100 |     100 |     100 |                   \n  ...te.service.ts |     100 |      100 |     100 |     100 |                   \n libs/payment/src  |     100 |      100 |     100 |     100 |                   \n  index.ts         |     100 |      100 |     100 |     100 |                   \n  types.ts         |     100 |      100 |     100 |     100 |                   \n ...t/src/gateways |     100 |    96.77 |     100 |     100 |                   \n  ...al.adapter.ts |     100 |    96.77 |     100 |     100 | 14                \n ...t/src/services |     100 |      100 |     100 |     100 |                   \n  ...cy.service.ts |     100 |      100 |     100 |     100 |                   \n  ...on.service.ts |     100 |      100 |     100 |     100 |                   \n libs/security/src |     100 |      100 |     100 |     100 |                   \n  auditor.ts       |     100 |      100 |     100 |     100 |                   \n  crypto.ts        |     100 |      100 |     100 |     100 |                   \n  hashing.ts       |     100 |      100 |     100 |     100 |                   \n  index.ts         |     100 |      100 |     100 |     100 |                   \n  rbac.ts          |     100 |      100 |     100 |     100 |                   \n  secrets.ts       |     100 |      100 |     100 |     100 |                   \n  token.ts         |     100 |      100 |     100 |     100 |                   \n ...urity/src/rbac |     100 |      100 |     100 |     100 |                   \n  model.ts         |     100 |      100 |     100 |     100 |                   \n-------------------|---------|----------|---------|---------|-------------------\n"
      }
    ]
  },
  "summary": {
    "ok": false,
    "coverage": {
      "root": false,
      "api": {
        "ok": false,
        "reason": "no-summary"
      },
      "rootSummary": {
        "ok": false,
        "total": {
          "lines": {
            "total": 651,
            "covered": 644,
            "skipped": 0,
            "pct": 98.92
          },
          "statements": {
            "total": 651,
            "covered": 644,
            "skipped": 0,
            "pct": 98.92
          },
          "functions": {
            "total": 123,
            "covered": 119,
            "skipped": 0,
            "pct": 96.74
          },
          "branches": {
            "total": 309,
            "covered": 299,
            "skipped": 0,
            "pct": 96.76
          },
          "branchesTrue": {
            "total": 0,
            "covered": 0,
            "skipped": 0,
            "pct": 100
          }
        }
      }
    },
    "compliance": {
      "wcag": {
        "standard": "WCAG 2.2 AAA",
        "status": "partially-automated",
        "checks": [
          {
            "id": "1.4.3",
            "name": "Contrast (Minimum)",
            "status": "manual/CI-lighthouse",
            "evidence": ["tests/accessibility.spec.ts (axe serious/critical)"]
          },
          {
            "id": "2.4.6",
            "name": "Headings and Labels",
            "status": "automated",
            "evidence": ["aria-label present in layout"]
          },
          {
            "id": "1.3.1",
            "name": "Info and Relationships",
            "status": "automated/partial",
            "evidence": ["jest-axe unit assertions"]
          },
          {
            "id": "2.1.1",
            "name": "Keyboard",
            "status": "manual",
            "evidence": []
          },
          {
            "id": "3.1.5",
            "name": "Reading Level (AAA)",
            "status": "manual",
            "evidence": []
          }
        ]
      },
      "nist": {
        "standard": "NIST 800-207 (ZTMM)",
        "status": "aligned-core-controls",
        "checks": [
          {
            "id": "mTLS",
            "status": "present",
            "evidence": ["apps/api/src/middleware/mtls.guard.ts", "libs/auth/src/mtls.ts"]
          },
          {
            "id": "RateLimiting",
            "status": "present",
            "evidence": ["apps/api/src/middleware/rate-limiter.network.ts"]
          },
          {
            "id": "Idempotency",
            "status": "present",
            "evidence": ["apps/api/src/middleware/idempotency.guard.ts"]
          },
          {
            "id": "DeviceBinding",
            "status": "present",
            "evidence": ["libs/auth/src/core/device-binding.ts"]
          },
          {
            "id": "TokenRotation",
            "status": "present",
            "evidence": ["libs/auth/src/rotation.ts", "libs/auth/src/core/session-store.ts"]
          },
          {
            "id": "RBAC",
            "status": "present",
            "evidence": ["libs/security/src/rbac.ts"]
          }
        ]
      },
      "pci": {
        "standard": "PCI-DSS v4.0.1",
        "status": "engineering-mapped",
        "checks": [
          {
            "id": "6.2",
            "name": "Secure coding",
            "status": "tests/coverage 100%",
            "evidence": ["vitest + security-auditor"]
          },
          {
            "id": "8.2",
            "name": "AuthN/AuthZ",
            "status": "present",
            "evidence": ["libs/auth tokens", "RBAC"]
          },
          {
            "id": "2.2.4",
            "name": "Strict services",
            "status": "present/infra",
            "evidence": ["ops/scripts/post-deploy-security-check.mjs"]
          },
          {
            "id": "4.2",
            "name": "Strong cryptography",
            "status": "present",
            "evidence": ["libs/security/src/crypto.ts", "hashing.ts"]
          },
          {
            "id": "11.3",
            "name": "Vulnerability scanning",
            "status": "static code scan",
            "evidence": ["ops/reports/security-auditor-final.mjs"]
          }
        ]
      }
    }
  }
}
